lzma_pyo3/lzma_pyo3.cpython-314-darwin.so
lzma_pyo3/__init__.py
hmt_lzma_pyo3-0.2.0.dist-info/RECORD
hmt_lzma_pyo3-0.2.0.dist-info/WHEEL
hmt_lzma_pyo3-0.2.0.dist-info/top_level.txt
hmt_lzma_pyo3-0.2.0.dist-info/METADATA
