Metadata-Version: 2.4
Name: hmt-lzma-pyo3
Version: 0.2.0
Summary: Python module based on the LZ-String javascript, purpose here is to be faster than existing native python implementation
License: The MIT License (MIT)
Classifier: License :: OSI Approved :: MIT License
Classifier: Development Status :: 3 - Alpha
Classifier: Intended Audience :: Developers
Classifier: Programming Language :: Python :: 3.9
Classifier: Programming Language :: Python :: 3.10
Classifier: Programming Language :: Python :: 3.11
Classifier: Programming Language :: Python :: 3.12
Classifier: Programming Language :: Python :: 3.13
Classifier: Programming Language :: Python :: 3.14
Classifier: Programming Language :: Rust
Classifier: Operating System :: POSIX
Requires-Python: >=3.9
